openocd/__init__.py
openocd/openocd.py
openocd/tclformatter.py
openocd-0.4.0.dist-info/licenses/LICENSE
openocd-0.4.0.dist-info/METADATA
openocd-0.4.0.dist-info/WHEEL
openocd-0.4.0.dist-info/top_level.txt
openocd-0.4.0.dist-info/RECORD
