Metadata-Version: 2.4
Name: openocd
Version: 0.4.0
Summary: Python interface library for OpenOCD
Home-page: https://gitlab.zapb.de/openocd/python-openocd
Author: Marc Schink
Author-email: dev@zapb.de
License: LGPL-2.1-or-later
Project-URL: Source, https://gitlab.zapb.de/openocd/python-openocd
Keywords: OpenOCD microcontroller debug embedded
Classifier: Development Status :: 3 - Alpha
Classifier: Programming Language :: Python :: 3
Classifier: Topic :: Software Development :: Embedded Systems
Requires-Python: >=3.10
License-File: LICENSE
Requires-Dist: typing_extensions>=4.5.0
Dynamic: author
Dynamic: author-email
Dynamic: classifier
Dynamic: description
Dynamic: description-content-type
Dynamic: home-page
Dynamic: keywords
Dynamic: license
Dynamic: license-file
Dynamic: project-url
Dynamic: requires-dist
Dynamic: requires-python
Dynamic: summary
